xhs_note_extractor/DEVICE_RETRY_GUIDE.md
xhs_note_extractor/__init__.py
xhs_note_extractor/_version.py
xhs_note_extractor/agent_login.py
xhs_note_extractor/cli.py
xhs_note_extractor/date_desc_utils.py
xhs_note_extractor/extractor.py
xhs_note_extractor/login_propmt.py
xhs_note_extractor/number_utils.py
xhs_note_extractor/sms_verification.py
xhs_note_extractor/test_device_retry.py
xhs_note_extractor/test_initialization_fix.py
xhs_note_extractor/utils.py
xhs_note_extractor-0.1.4.dist-info/licenses/LICENSE
xhs_note_extractor-0.1.4.dist-info/METADATA
xhs_note_extractor-0.1.4.dist-info/WHEEL
xhs_note_extractor-0.1.4.dist-info/entry_points.txt
xhs_note_extractor-0.1.4.dist-info/top_level.txt
xhs_note_extractor-0.1.4.dist-info/RECORD
