Metadata-Version: 2.4
Name: xhs-note-extractor
Version: 0.1.4
Summary: A Python package for extracting Xiaohongshu (Little Red Book) note data from URLs
Author-email: JoyCode Agent <agent@joycode.com>
License: MIT
Project-URL: Homepage, https://github.com/yehao20/xhs-note-extractor
Project-URL: Repository, https://github.com/yehao20/xhs-note-extractor
Project-URL: Documentation, https://github.com/yehao20/xhs-note-extractor/blob/main/README.md
Project-URL: Issues, https://github.com/yehao20/xhs-note-extractor/issues
Keywords: xiaohongshu,little-red-book,web-scraping,automation,uiautomator
Classifier: Development Status :: 4 - Beta
Classifier: Intended Audience :: Developers
Classifier: License :: OSI Approved :: MIT License
Classifier: Operating System :: OS Independent
Classifier: Programming Language :: Python :: 3
Classifier: Programming Language :: Python :: 3.8
Classifier: Programming Language :: Python :: 3.9
Classifier: Programming Language :: Python :: 3.10
Classifier: Programming Language :: Python :: 3.11
Classifier: Programming Language :: Python :: 3.12
Classifier: Topic :: Software Development :: Libraries :: Python Modules
Classifier: Topic :: Internet :: WWW/HTTP
Classifier: Topic :: Utilities
Requires-Python: >=3.8
License-File: LICENSE
Requires-Dist: uiautomator2>=2.16.17
Requires-Dist: requests>=2.25.0
Requires-Dist: playwright>=1.48.0
Requires-Dist: typing-extensions>=4.13.2
Requires-Dist: pydantic>=2.10.6
Provides-Extra: dev
Requires-Dist: pytest>=6.0; extra == "dev"
Requires-Dist: pytest-cov>=2.0; extra == "dev"
Requires-Dist: black>=21.0; extra == "dev"
Requires-Dist: flake8>=3.8; extra == "dev"
Dynamic: license-file
